easy_orm/__init__.py
easy_orm/__init__.pyi
easy_orm/easy_orm.cp312-win_amd64.pyd
easy_orm/exception.cp312-win_amd64.pyd
easy_orm/db/__init__.py
easy_orm/db/sql_session.cp312-win_amd64.pyd
easy_orm/db/sql_template.cp312-win_amd64.pyd
easy_orm/mapper/__init__.py
easy_orm/mapper/mapper_parse.cp312-win_amd64.pyd
easy_orm/utils/__init__.py
easy_orm/utils/funs.cp312-win_amd64.pyd
easy_orm/utils/sql_params.cp312-win_amd64.pyd
easy_orm/utils/sql_util.cp312-win_amd64.pyd
easy_orm/utils/string_util.cp312-win_amd64.pyd
easy_orm/utils/type_util.cp312-win_amd64.pyd
easyorm_py-1.0.25.dist-info/METADATA
easyorm_py-1.0.25.dist-info/WHEEL
easyorm_py-1.0.25.dist-info/top_level.txt
easyorm_py-1.0.25.dist-info/RECORD
