Metadata-Version: 2.4
Name: easyorm-py
Version: 1.0.25
Summary: easy_orm
Requires-Python: >=3.6
Dynamic: description
Dynamic: description-content-type
Dynamic: requires-python
Dynamic: summary
